lookatme/__init__.py
lookatme/__main__.py
lookatme/ascii_art.py
lookatme/config.py
lookatme/exceptions.py
lookatme/log.py
lookatme/parser.py
lookatme/pres.py
lookatme/prompt.py
lookatme/schemas.py
lookatme/slide.py
lookatme/tui.py
lookatme/tutorial.py
lookatme/utils.py
lookatme/contrib/__init__.py
lookatme/contrib/file_loader.py
lookatme/contrib/terminal.py
lookatme/render/__init__.py
lookatme/render/asciinema.py
lookatme/render/markdown_block.py
lookatme/render/markdown_inline.py
lookatme/render/pygments.py
lookatme/themes/__init__.py
lookatme/themes/dark.py
lookatme/themes/light.py
lookatme/widgets/__init__.py
lookatme/widgets/clickable_text.py
lookatme/widgets/table.py
lookatme-2.5.5.dist-info/LICENSE
lookatme-2.5.5.dist-info/METADATA
lookatme-2.5.5.dist-info/WHEEL
lookatme-2.5.5.dist-info/entry_points.txt
lookatme-2.5.5.dist-info/top_level.txt
lookatme-2.5.5.dist-info/RECORD
