Metadata-Version: 2.1
Name: lookatme
Version: 2.5.5
Summary: An interactive, command-line presentation tool
Home-page: https://github.com/d0c-s4vage/lookatme
Author: James Johnson
Author-email: d0c.s4vage@gmail.com
Classifier: Environment :: Console
Classifier: Environment :: Plugins
Classifier: Intended Audience :: Developers
Classifier: License :: OSI Approved :: MIT License
Classifier: Operating System :: OS Independent
Classifier: Programming Language :: Python :: 3
Classifier: Programming Language :: Python :: 3 :: Only
Classifier: Topic :: Multimedia :: Graphics :: Presentation
Classifier: Topic :: Software Development :: Documentation
Requires-Python: >=3.6
License-File: LICENSE
Requires-Dist: marshmallow (<4,>=3.17.0)
Requires-Dist: Click (<9,>=7)
Requires-Dist: PyYAML (<6,>=5)
Requires-Dist: mistune (<1,>=0.8)
Requires-Dist: urwid (<3,>=2)
Requires-Dist: Pygments (<3,>=2)
